build_backends/__init__.py
build_backends/main.py
build_backends/main_prd.py
flowfile/__init__.py
flowfile/__main__.py
flowfile/api.py
flowfile/web/__init__.py
flowfile/web/static/assets/AdminView-B2Dthl3u.css
flowfile/web/static/assets/AdminView-pLK3xKht.js
flowfile/web/static/assets/CloudConnectionView-Ba6Wq47L.js
flowfile/web/static/assets/CloudConnectionView-BdFYGWV7.css
flowfile/web/static/assets/CloudStorageReader-BDByiqPI.css
flowfile/web/static/assets/CloudStorageReader-DrRS7OWy.js
flowfile/web/static/assets/CloudStorageWriter-DGC5_ZUo.js
flowfile/web/static/assets/CloudStorageWriter-y8jL8yjG.css
flowfile/web/static/assets/ColumnActionInput-Dv9zy9e0.js
flowfile/web/static/assets/ColumnActionInput-dCasSIC9.css
flowfile/web/static/assets/ColumnSelector-CM0ObHXB.js
flowfile/web/static/assets/ColumnSelector-j6sEOjo1.css
flowfile/web/static/assets/ContextMenu-BAs9H_Wh.js
flowfile/web/static/assets/ContextMenu-C2xwZLRH.js
flowfile/web/static/assets/ContextMenu-qSOvoPpb.js
flowfile/web/static/assets/ContextMenu.vue_vue_type_script_setup_true_lang-C_BmmKoB.js
flowfile/web/static/assets/CrossJoin-Cmbyt9im.css
flowfile/web/static/assets/CrossJoin-Dld8z_IH.js
flowfile/web/static/assets/CustomNode-By0e3nWL.js
flowfile/web/static/assets/CustomNode-VPlajG0j.css
flowfile/web/static/assets/DatabaseConnectionSettings-B78hXYgu.css
flowfile/web/static/assets/DatabaseConnectionSettings-BQ_zK4Ow.js
flowfile/web/static/assets/DatabaseReader-D6pUNUCs.css
flowfile/web/static/assets/DatabaseReader-DvJHkeu3.js
flowfile/web/static/assets/DatabaseView-B-_adk1s.css
flowfile/web/static/assets/DatabaseView-rwAonZJD.js
flowfile/web/static/assets/DatabaseWriter-D4B89zec.js
flowfile/web/static/assets/DatabaseWriter-RBqdFLj8.css
flowfile/web/static/assets/DesignerView-BJNT6s6o.js
flowfile/web/static/assets/DesignerView-Dm6OzlIc.css
flowfile/web/static/assets/DocumentationView-BHvVcyuM.js
flowfile/web/static/assets/DocumentationView-CL7iipFL.css
flowfile-0.6.2.dist-info/METADATA
flowfile-0.6.2.dist-info/WHEEL
flowfile-0.6.2.dist-info/entry_points.txt
flowfile-0.6.2.dist-info/licenses/LICENSE
flowfile-0.6.2.dist-info/RECORD
