Metadata-Version: 2.4
Name: Flowfile
Version: 0.6.2
Summary: Project combining flowfile core (backend) and flowfile_worker (compute offloader) and flowfile_frame (api)
License-File: LICENSE
Author: Edward van Eechoud
Author-email: evaneechoud@gmail.com
Requires-Python: >=3.10,<3.14
Classifier: Programming Language :: Python :: 3
Classifier: Programming Language :: Python :: 3.10
Classifier: Programming Language :: Python :: 3.11
Classifier: Programming Language :: Python :: 3.12
Classifier: Programming Language :: Python :: 3.13
Requires-Dist: XlsxWriter (>=3.2.0,<3.3.0)
Requires-Dist: aiofiles (>=24.1.0,<25.0.0)
Requires-Dist: bcrypt (>=4.3.0,<5.0.0)
Requires-Dist: boto3 (>=1.38.40,<1.38.47)
Requires-Dist: connectorx (>=0.4.2,<0.5.0)
Requires-Dist: cryptography (>=45.0.5,<46.0.0)
Requires-Dist: databases (>=0.9.0,<0.10.0)
Requires-Dist: deltalake (>=1.1.0,<2.0.0)
Requires-Dist: faker (>=23.1.0,<23.2.0)
Requires-Dist: fastapi (>=0.115.2,<0.116.0)
Requires-Dist: fastexcel (>=0.12.0,<0.13.0)
Requires-Dist: httpx (>=0.28.1,<0.29.0)
Requires-Dist: loky (>=3.4.1,<3.5.0)
Requires-Dist: methodtools (>=0.4.7,<0.5.0)
Requires-Dist: openpyxl (>=3.1.2,<3.2.0)
Requires-Dist: passlib (>=1.7.4,<1.8.0)
Requires-Dist: pendulum (==2.1.2) ; python_version < "3.12"
Requires-Dist: pl-fuzzy-frame-match (>=0.4.0)
Requires-Dist: polars (>=1.8.2,<1.32) ; sys_platform != "win32"
Requires-Dist: polars (>=1.8.2,<=1.25.2) ; sys_platform == "win32"
Requires-Dist: polars-distance (>=0.4.3,<0.5.0)
Requires-Dist: polars-ds (>=0.6.0)
Requires-Dist: polars-expr-transformer (>=0.5.0)
Requires-Dist: polars-grouper (>=0.3.0,<0.4.0)
Requires-Dist: polars_simed (>=0.3.4,<0.4.0)
Requires-Dist: pyarrow (>=18.0.0,<19.0.0)
Requires-Dist: pydantic (>=2.9.2,<2.10.0)
Requires-Dist: pyiceberg[hadoop] (>=0.9.1,<0.10.0)
Requires-Dist: python-jose (>=3.4.0,<4.0.0)
Requires-Dist: python-multipart (>=0.0.12,<0.1.0)
Requires-Dist: pyyaml (>=6.0.3,<7.0.0)
Requires-Dist: s3fs (>=2025.7.0,<2026.0.0)
Requires-Dist: tqdm (>=4.67.1,<5.0.0)
Requires-Dist: uvicorn (>=0.32.0,<0.33.0)
Requires-Dist: websockets (>=12.0)
